setup.py
lite_interface_bot/__init__.py
lite_interface_bot/basic_handler.py
lite_interface_bot/bot.py
lite_interface_bot/callback_data_filter.py
lite_interface_bot/utils.py
lite_interface_bot.egg-info/PKG-INFO
lite_interface_bot.egg-info/SOURCES.txt
lite_interface_bot.egg-info/dependency_links.txt
lite_interface_bot.egg-info/requires.txt
lite_interface_bot.egg-info/top_level.txt