Metadata-Version: 2.1
Name: lite-interface-bot
Version: 1.0
Summary: Прототип легкого інтерфейсу для aiogram
Home-page: UNKNOWN
Author: Floms
Author-email: jeka.floms@gmail.com
License: MIT
Platform: UNKNOWN
